bowerstatic
