Metadata-Version: 1.0
Name: bowerstatic
Version: 0.8.1
Summary: A Bower-centric static file server for WSGI
Home-page: http://bowerstatic.readthedocs.org
Author: Martijn Faassen
Author-email: faassen@startifact.com
License: BSD
Keywords: wsgi bower
Platform: UNKNOWN
